[
	{
		"name": "Комендант общежития богинь",
		"genre": "Этти, Гарем, Комедия",
		"id": "1",
		"status": "Вышел"
	},
	{
		"name": "Дневник будущего",
		"genre": "Триллер, Детектив, Психологическое",
		"id": "2",
		"status": "Вышел"
	},
	{
		"name": "Развращённая гильдия",
		"genre": "Этти, Гарем, Комедия",
		"id": "3",
		"status": "Вышел"
	},
	{
		"name": "Терраса кафе богинь",
		"genre": "Романтика, Гарем, Комедия",
		"id": "4",
		"status": "Вышел"
	},
	{
		"name": "Аля иногда кокетничает со мной по-русски",
		"genre": "Школа, Комедия, Романтика",
		"id": "5",
		"status": "—"
	},
	{
		"name": "Девушка на час",
		"genre": "Романтика, Комедия, Гарем",
		"id": "6",
		"status": "Требуется обновление данных"
	},
	{
		"name": "Пять невест",
		"genre": "Гарем, Комедия, Романтика",
		"id": "7",
		"status": "Вышел"
	},
	{
		"name": "Девушки на линии фронта",
		"genre": "Военное, Фантастика, Драма",
		"id": "8",
		"status": "Вышел"
	},
	{
		"name": "Студия, солнечная сторона, есть ангел",
		"genre": "Гарем, Комедия, Романтика",
		"id": "9",
		"status": "Вышел"
	},
	{
		"name": "Ангел по соседству",
		"genre": "Романтика, Школа, Повседневность",
		"id": "10",
		"status": "Требуется обновление данных"
	},
	{
		"name": "Неразумный ангел в танце с демоном",
		"genre": "Комедия, Романтика, Сверхъестественное",
		"id": "11",
		"status": "Вышел"
	},
	{
		"name": "Унеси меня на Луну",
		"genre": "Комедия, Романтика, Школа",
		"id": "12",
		"status": "—"
	},
	{
		"name": "Жизнь с моей сводной сестрой",
		"genre": "Романтика",
		"id": "13",
		"status": "—"
	},
	{
		"name": "Псевдогарем",
		"genre": "Комедия, Романтика",
		"id": "14",
		"status": "Вышел"
	},
	{
		"name": "Слушайтесь папу!",
		"genre": "Комедия, Романтика",
		"id": "15",
		"status": "Вышел"
	},
	{
		"name": "Моя девушка и подруга детства часто ссорятся",
		"genre": "Комедия, Романтика, Гарем",
		"id": "16",
		"status": "Вышел"
	},
	{
		"name": "Волшебница и злой офицер",
		"genre": "Комедия, Романтика",
		"id": "17",
		"status": "—"
	},
	{
		"name": "Последнее поле брани между тобой и мной, или Святая война сотворения мира",
		"genre": "Экшен, Фэнтези, Романтика",
		"id": "18",
		"status": "—"
	},
	{
		"name": "Может, я встречу тебя в подземелье?",
		"genre": "Экшен, Приключение, Фэнтези",
		"id": "19",
		"status": "—"
	},
	{
		"name": "Мифический дух: Хроники",
		"genre": "Гарем, Приключение, Реинкарнация ",
		"id": "20",
		"status": "—"
	},
	{
		"name": "Голубая шкатулка",
		"genre": "Школа, Романтика, Спорт",
		"id": "21",
		"status": "—"
	},
	{
		"name": "Брачные узы с семьёй Амагами",
		"genre": "Комедия, Романтика, Сверхъестественное",
		"id": "22",
		"status": "Вышел"
	},
	{
		"name": "Лунное путешествие приведёт к новому миру",
		"genre": "Экшен, Приключение, Комедия",
		"id": "23",
		"status": "—"
	},
	{
		"name": "Укротитель зверей, изгнанный из команды героя, встретил девочку-кошку из сильнейшей расы",
		"genre": "Экшен, Приключение, Фэнтези",
		"id": "24",
		"status": "—"
	},
	{
		"name": "Добро пожаловать в класс превосходства",
		"genre": "Триллер, Психологическое, Школа",
		"id": "25",
		"status": "Требуется обновление данных"
	},
	{
		"name": "Шпионский класс",
		"genre": "Экшен, Тайна",
		"id": "26",
		"status": "—"
	},
	{
		"name": "О моём перерождении в слизь️",
		"genre": "Фэнтези, Комедия, Приключение",
		"id": "27",
		"status": "—"
	},
	{
		"name": "Re: Жизнь в альтернативном мире с нуля",
		"genre": "Фэнтези, Приключение",
		"id": "28",
		"status": "Требуется обновление данных"
	},
	{
		"name": "Нападение одиночки на иной мир",
		"genre": "Экшен, Приключение, Исэкай",
		"id": "29",
		"status": "—"
	},
	{
		"name": "У Коми проблемы с общением",
		"genre": "Комедия, Школа",
		"id": "30",
		"status": "—"
	},
	{
		"name": "Моя геройская академия",
		"genre": "Экшен, Школа",
		"id": "31",
		"status": "Требуется обновление данных"
	},
	{
		"name": "Индекс волшебства",
		"genre": "Экшен, Фэнтези, Фантастика",
		"id": "32",
		"status": "—"
	},
	{
		"name": "Дандадан",
		"genre": "Комедия, Фэнтези, Фантастика",
		"id": "33",
		"status": "—"
	},
	{
		"name": "Рубеж Шангри-Ла: Любитель игрошлака бросает вызов топ-игре",
		"genre": "Экшен, Приключение, Видеоигры",
		"id": "34",
		"status": "—"
	},
	{
		"name": "Повелитель",
		"genre": "Экшен, Приключение, Фэнтези",
		"id": "35",
		"status": "—"
	},
//*⬇️
	{
		"name": "Моб Психо 100",
		"genre": "",
		"id": "36",
		"status": "—"
	},
	{
		"name": "Этот замечательный мир!",
		"genre": "",
		"id": "37",
		"status": "—"
	},
	{
		"name": "Сто девушек, которые очень-очень-очень-очень-очень сильно тебя любят",
		"genre": "",
		"id": "38",
		"status": "—"
	},
	{
		"name": "Провожающая в последний путь Фрирен",
		"genre": "",
		"id": "39",
		"status": "—"
	},
	{
		"name": "Хоримия",
		"genre": "",
		"id": "40",
		"status": "—"
	},
	{
		"name": "Я женился на однокласснице, которую ненавидел",
		"genre": "",
		"id": "41",
		"status": "—"
	},
	{
		"name": "Эта фарфоровая кукла влюбилась",
		"genre": "",
		"id": "42",
		"status": "—"
	},
	{
		"name": "Звёздное дитя",
		"genre": "",
		"id": "43",
		"status": "—"
	},
	{
		"name": "Сладкий лимонад",
		"genre": "",
		"id": "44",
		"status": "—"
	},
	{
		"name": "Дни Сакамото",
		"genre": "",
		"id": "45",
		"status": "—"
	},
	{
		"name": "Мой счастливый брак",
		"genre": "",
		"id": "46",
		"status": "—"
	},
	{
		"name": "Кайдзю №8",
		"genre": "",
		"id": "47",
		"status": "—"
	},
	{
		"name": "Туалетный мальчик Ханако",
		"genre": "",
		"id": "48",
		"status": "—"
	},
	{
		"name": "Непостижимая Ахарэн",
		"genre": "",
		"id": "49",
		"status": "—"
	},
	{
		"name": "Магическая битва",
		"genre": "",
		"id": "50",
		"status": "—"
	},
	{
		"name": "Магия и мускулы",
		"genre": "",
		"id": "51",
		"status": "—"
	},
	{
		"name": "Нежити не повезло",
		"genre": "",
		"id": "52",
		"status": "—"
	},
	{
		"name": "Я секретарь гильдии, но я не люблю сверхурочную работу, поэтому я собираюсь подчинить босса в одиночку",
		"genre": "",
		"id": "53",
		"status": "—"
	},
	{
		"name": "Может ли существовать дружба между мужчиной и женщиной? (Нет, это не так!)",
		"genre": "",
		"id": "54",
		"status": "—"
	},
	{
		"name": "Больше чем пара, меньше чем любовники",
		"genre": "",
		"id": "55",
		"status": "—"
	},
	{
		"name": "Карманы лета",
		"genre": "",
		"id": "56",
		"status": "—"
	},
	{
		"name": "Необъятный океан",
		"genre": "",
		"id": "57",
		"status": "—"
	},
	{
		"name": "Синий архив",
		"genre": "",
		"id": "58",
		"status": "—"
	},
	{
		"name": "Сведённые кукушкой",
		"genre": "",
		"id": "59",
		"status": "—"
	},
	{
		"name": "Адзуманга Дайо",
		"genre": "",
		"id": "60",
		"status": "Вышел"
	},
	{
		"name": "Ван-Пис",
		"genre": "",
		"id": "61",
		"status": "—"
	},
	{
		"name": "Этот глупый свин не понимает мечту девочки-зайки",
		"genre": "",
		"id": "62",
		"status": "—"
	},
	{
		"name": "Мэдака Куроива не понимает моей привлекательности",
		"genre": "",
		"id": "63",
		"status": "—"
	},
	{
		"name": "Проект «Мир»: Сломанный мир и непоющая Мику",
		"genre": "",
		"id": "64",
		"status": "—"
	},
	{
		"name": "Предсмертный список зомби",
		"genre": "",
		"id": "65",
		"status": "—"
	},
	{
		"name": "Киберпанк: Бегущие по краю",
		"genre": "",
		"id": "66",
		"status": "—"
	},
	{
		"name": "Прячься, Макина!",
		"genre": "",
		"id": "67",
		"status": "—"
	},
	{
		"name": "Как и ожидалось, моя школьная романтическая жизнь не удалась",
		"genre": "",
		"id": "68",
		"status": "—"
	},
	{
		"name": "Песнь ночных сов",
		"genre": "",
		"id": "69",
		"status": "—"
	},
	{
		"name": "Соседнему королевству продали святую, помолвку которой разорвали из-за того, что она стала слишком совершенной",
		"genre": "",
		"id": "70",
		"status": "—"
	},
	{
		"name": "Госпожа Кагуя: в любви как на войне",
		"genre": "",
		"id": "71",
		"status": "—"
	},
	{
		"name": "Поднятие уровня в одиночку",
		"genre": "",
		"id": "72",
		"status": "—"
	},
	{
		"name": "Семья шпиона",
		"genre": "",
		"id": "73",
		"status": "—"
	},
	{
		"name": "Ванпанчмен",
		"genre": "",
		"id": "74",
		"status": "—"
	},
	{
		"name": "Величайший Повелитель Демонов перерождается как типичное ничтожество",
		"genre": "",
		"id": "75",
		"status": "—"
	},
	{
		"name": "Дьявол может плакать",
		"genre": "",
		"id": "76",
		"status": "—"
	},
	{
		"name": "Первородный грех Такопи",
		"genre": "",
		"id": "77",
		"status": "—"
	},
	{
		"name": "Благоухающий цветок расцветает с достоинством",
		"genre": "",
		"id": "78",
		"status": "—"
	},
	{
		"name": "Хёка",
		"genre": "",
		"id": "79",
		"status": "—"
	},
	{
		"name": "Опасность в моём сердце",
		"genre": "",
		"id": "80",
		"status": "—"
	},
	{
		"name": "Грисайя",
		"genre": "",
		"id": "81",
		"status": "—"
	},
	{
		"name": "Тирания вооруженных девушек",
		"genre": "",
		"id": "82",
		"status": "—"
	},
	{
		"name": "Твоя апрельская ложь",
		"genre": "",
		"id": "83",
		"status": "—"
	},
	{
		"name": "Достучаться до тебя",
		"genre": "",
		"id": "84",
		"status": "—"
	},
	{
		"name": "История знакомства опытной тебя и неопытного меня",
		"genre": "",
		"id": "85",
		"status": "—"
	},
	{
		"name": "Создай девушку",
		"genre": "",
		"id": "86",
		"status": "—"
	},
	{
		"name": "Моя девушка не только милая",
		"genre": "",
		"id": "87",
		"status": "—"
	},
	{
		"name": "Плачущий призрак на пенсии",
		"genre": "",
		"id": "88",
		"status": "—"
	},
	{
		"name": "Самый известный диктор создаёт самый великий в мире клан",
		"genre": "",
		"id": "89",
		"status": "—"
	},
	{
		"name": "Реинкарнация безработного: История о приключениях в другом мире",
		"genre": "",
		"id": "90",
		"status": "—"
	},
	{
		"name": "Дисквалифицирован по жизни",
		"genre": "",
		"id": "91",
		"status": "—"
	},
	{
		"name": "Удзаки хочет тусоваться!",
		"genre": "",
		"id": "92",
		"status": "—"
	},
	{
		"name": "Маленькая сэмпай с моей работы",
		"genre": "",
		"id": "93",
		"status": "—"
	},
	{
		"name": "Магическая академия Атараксия: Гибрид x Сердце",
		"genre": "",
		"id": "94",
		"status": "—"
	},
	{
		"name": "Читерский навык из другого мира сделал меня непобедимым в моём",
		"genre": "",
		"id": "95",
		"status": "—"
	},
	{
		"name": "Мастер демонического клинка из академии «Святого Меча»",
		"genre": "",
		"id": "96",
		"status": "—"
	},
	{
		"name": "Дети семьи Сиундзи",
		"genre": "",
		"id": "97",
		"status": "—"
	},
	{
		"name": "Эй, люби меня всерьёз!",
		"genre": "",
		"id": "98",
		"status": "—"
	},
	{
		"name": "Рандеву с жизнью",
		"genre": "",
		"id": "99",
		"status": "—"
	},
	{
		"name": "Гениальный целитель, который исцелял в одно мгновение, но был изгнан как бесполезный, теперь наслаждается жизнью в качестве тёмного целителя",
		"genre": "",
		"id": "100",
		"status": "—"
	},
	{
		"name": "Мастера меча онлайн",
		"genre": "",
		"id": "101",
		"status": "—"
	},
	{
		"name": "Непризнанный школой владыка демонов",
		"genre": "",
		"id": "102",
		"status": "—"
	},
	{
		"name": "В симуляторе свиданий: Нелёгкая жизнь мобов в мире отомэ-игр",
		"genre": "",
		"id": "103",
		"status": "—"
	},
	{
		"name": "Любовь и неприятности",
		"genre": "",
		"id": "104",
		"status": "—"
	},
	{
		"name": "Нахальный принц и кошка-несмеяна",
		"genre": "",
		"id": "105",
		"status": "—"
	},
	{
		"name": "Я, владыка демонов, взял эльфийку-рабыню в жёны. И как же мне её любить?",
		"genre": "",
		"id": "106",
		"status": "—"
	},
	{
		"name": "Безэмоциональная Кашивада и эмоциональный Ота",
		"genre": "",
		"id": "107",
		"status": "—"
	},
	{
		"name": "Младшая сестра моего друга досаждает",
		"genre": "",
		"id": "108",
		"status": "—"
	},
	{
		"name": "Храм: Никто не может жить в одиночестве",
		"genre": "",
		"id": "109",
		"status": "—"
	},
	{
		"name": "Восхождение в тени!",
		"genre": "",
		"id": "110",
		"status": "—"
	},
	{
		"name": "Другой мир не может противостоять силе мгновенной смерти",
		"genre": "",
		"id": "111",
		"status": "—"
	},
	{
		"name": "Новые врата",
		"genre": "",
		"id": "112",
		"status": "—"
	},
	{
		"name": "Рыцарь-скелет вступает в параллельный мир",
		"genre": "",
		"id": "113",
		"status": "—"
	},
	{
		"name": "Герой-рационал перестраивает королевство",
		"genre": "",
		"id": "114",
		"status": "—"
	},
	{
		"name": "Проект «Белая Кошка»",
		"genre": "",
		"id": "115",
		"status": "—"
	},
	{
		"name": "Неспешная жизнь уволенного тёмного солдата (тридцати лет)",
		"genre": "",
		"id": "116",
		"status": "—"
	},
	{
		"name": "Юна из гостиницы Юраги",
		"genre": "",
		"id": "117",
		"status": "—"
	},
	{
		"name": "Бесклассовый герой: Да мне всё равно не нужны эти ваши умения",
		"genre": "",
		"id": "118",
		"status": "—"
	},
	{
		"name": "Я злой лорд межгалактической империи!",
		"genre": "",
		"id": "119",
		"status": "—"
	},
	{
		"name": "XX Ватари на грани краха",
		"genre": "",
		"id": "120",
		"status": "—"
	},
	{
		"name": "Милый во франксе",
		"genre": "",
		"id": "121",
		"status": "—"
	},
	{
		"name": "Создатель магии: Как создать волшебство в другом мире",
		"genre": "",
		"id": "122",
		"status": "—"
	},
	{
		"name": "Механическая Мари",
		"genre": "",
		"id": "123",
		"status": "—"
	},
	{
		"name": "Любовь с кончиков пальцев",
		"genre": "",
		"id": "124",
		"status": "—"
	},
	{
		"name": "Битва через 5 секунд после встречи",
		"genre": "",
		"id": "125",
		"status": "—"
	},
	{
		"name": "Хроники Акаши — худшего магического преподавателя",
		"genre": "",
		"id": "126",
		"status": "—"
	},
	{
		"name": "Плачущий призрак на пенсии",
		"genre": "",
		"id": "127",
		"status": "—"
	},
	{
		"name": "Руководство гениального принца по вызволению страны из долгов",
		"genre": "",
		"id": "128",
		"status": "—"
	},
	{
		"name": "Призванный в другой мир во второй раз",
		"genre": "",
		"id": "129",
		"status": "—"
	},
	{
		"name": "Проиграйте, чтобы разбогатеть с самого начала игры",
		"genre": "",
		"id": "130",
		"status": "—"
	},
	{
		"name": "Сильнейший мудрец со слабейшей меткой",
		"genre": "",
		"id": "131",
		"status": "—"
	},
	{
		"name": "Добро пожаловать в Японию! Госпожа Эльф!",
		"genre": "",
		"id": "132",
		"status": "—"
	},
	{
		"name": "Сильнейший герой, обученный в тайном подземелье",
		"genre": "",
		"id": "133",
		"status": "—"
	},
	{
		"name": "Доктор Стоун",
		"genre": "",
		"id": "134",
		"status": "—"
	},
	{
		"name": "Ты и я — полные противоположности",
		"genre": "",
		"id": "135",
		"status": "—"
	}
]